[{"timestamp":1624341122262,"files":[{"filename":"ssr-bundle.db5e5.css","previous":850,"size":0,"diff":-850},{"filename":"ssr-bundle.js","previous":13496,"size":0,"diff":-13496},{"filename":"bundle.66656.css","previous":0,"size":645,"diff":645},{"filename":"bundle.*****.esm.js","previous":0,"size":9582,"diff":9582},{"filename":"polyfills.*****.esm.js","previous":0,"size":2173,"diff":2173},{"filename":"route-about/index.tsx.chunk.00f33.css","previous":0,"size":75,"diff":75},{"filename":"route-about/index.tsx.chunk.*****.esm.js","previous":0,"size":730,"diff":730},{"filename":"route-art/index.tsx.chunk.5684c.css","previous":0,"size":73,"diff":73},{"filename":"route-art/index.tsx.chunk.*****.esm.js","previous":0,"size":337,"diff":337},{"filename":"route-bylaws/index.tsx.chunk.d6322.css","previous":0,"size":100,"diff":100},{"filename":"route-bylaws/index.tsx.chunk.*****.esm.js","previous":0,"size":8448,"diff":8448},{"filename":"route-contact/index.tsx.chunk.e324c.css","previous":0,"size":77,"diff":77},{"filename":"route-contact/index.tsx.chunk.*****.esm.js","previous":0,"size":534,"diff":534},{"filename":"route-home/index.tsx.chunk.e6c71.css","previous":0,"size":74,"diff":74},{"filename":"route-home/index.tsx.chunk.*****.esm.js","previous":0,"size":335,"diff":335},{"filename":"route-notfound/index.tsx.chunk.740b8.css","previous":0,"size":78,"diff":78},{"filename":"route-notfound/index.tsx.chunk.*****.esm.js","previous":0,"size":401,"diff":401},{"filename":"sw-esm.js","previous":0,"size":8457,"diff":8457},{"filename":"sw.js","previous":0,"size":8453,"diff":8453},{"filename":"bundle.f89f5.js","previous":0,"size":9554,"diff":9554},{"filename":"polyfills.2854d.js","previous":0,"size":2169,"diff":2169},{"filename":"route-about/index.tsx.chunk.b1496.js","previous":0,"size":731,"diff":731},{"filename":"route-art/index.tsx.chunk.2ae9c.js","previous":0,"size":341,"diff":341},{"filename":"route-bylaws/index.tsx.chunk.21202.js","previous":0,"size":8451,"diff":8451},{"filename":"route-contact/index.tsx.chunk.c46fb.js","previous":0,"size":535,"diff":535},{"filename":"route-home/index.tsx.chunk.a17d7.js","previous":0,"size":338,"diff":338},{"filename":"route-notfound/index.tsx.chunk.6e459.js","previous":0,"size":403,"diff":403}]},{"timestamp":1624341107763,"files":[{"filename":"bundle.66656.css","previous":645,"size":0,"diff":-645},{"filename":"bundle.*****.esm.js","previous":9582,"size":0,"diff":-9582},{"filename":"polyfills.*****.esm.js","previous":2173,"size":0,"diff":-2173},{"filename":"route-about/index.tsx.chunk.00f33.css","previous":75,"size":0,"diff":-75},{"filename":"route-about/index.tsx.chunk.*****.esm.js","previous":730,"size":0,"diff":-730},{"filename":"route-art/index.tsx.chunk.5684c.css","previous":73,"size":0,"diff":-73},{"filename":"route-art/index.tsx.chunk.*****.esm.js","previous":337,"size":0,"diff":-337},{"filename":"route-bylaws/index.tsx.chunk.d6322.css","previous":100,"size":0,"diff":-100},{"filename":"route-bylaws/index.tsx.chunk.*****.esm.js","previous":8448,"size":0,"diff":-8448},{"filename":"route-contact/index.tsx.chunk.e324c.css","previous":77,"size":0,"diff":-77},{"filename":"route-contact/index.tsx.chunk.*****.esm.js","previous":534,"size":0,"diff":-534},{"filename":"route-home/index.tsx.chunk.e6c71.css","previous":74,"size":0,"diff":-74},{"filename":"route-home/index.tsx.chunk.*****.esm.js","previous":335,"size":0,"diff":-335},{"filename":"route-notfound/index.tsx.chunk.740b8.css","previous":78,"size":0,"diff":-78},{"filename":"route-notfound/index.tsx.chunk.*****.esm.js","previous":401,"size":0,"diff":-401},{"filename":"sw-esm.js","previous":8457,"size":0,"diff":-8457},{"filename":"sw.js","previous":8453,"size":0,"diff":-8453},{"filename":"bundle.f89f5.js","previous":9554,"size":0,"diff":-9554},{"filename":"polyfills.2854d.js","previous":2169,"size":0,"diff":-2169},{"filename":"route-about/index.tsx.chunk.b1496.js","previous":731,"size":0,"diff":-731},{"filename":"route-art/index.tsx.chunk.2ae9c.js","previous":341,"size":0,"diff":-341},{"filename":"route-bylaws/index.tsx.chunk.21202.js","previous":8451,"size":0,"diff":-8451},{"filename":"route-contact/index.tsx.chunk.c46fb.js","previous":535,"size":0,"diff":-535},{"filename":"route-home/index.tsx.chunk.a17d7.js","previous":338,"size":0,"diff":-338},{"filename":"route-notfound/index.tsx.chunk.6e459.js","previous":403,"size":0,"diff":-403},{"filename":"ssr-bundle.db5e5.css","previous":0,"size":850,"diff":850},{"filename":"ssr-bundle.js","previous":0,"size":13496,"diff":13496}]},{"timestamp":1624340941097,"files":[{"filename":"ssr-bundle.db5e5.css","previous":850,"size":0,"diff":-850},{"filename":"ssr-bundle.js","previous":13496,"size":0,"diff":-13496},{"filename":"bundle.66656.css","previous":0,"size":645,"diff":645},{"filename":"bundle.*****.esm.js","previous":0,"size":9582,"diff":9582},{"filename":"polyfills.*****.esm.js","previous":0,"size":2173,"diff":2173},{"filename":"route-about/index.tsx.chunk.00f33.css","previous":0,"size":75,"diff":75},{"filename":"route-about/index.tsx.chunk.*****.esm.js","previous":0,"size":730,"diff":730},{"filename":"route-art/index.tsx.chunk.5684c.css","previous":0,"size":73,"diff":73},{"filename":"route-art/index.tsx.chunk.*****.esm.js","previous":0,"size":337,"diff":337},{"filename":"route-bylaws/index.tsx.chunk.d6322.css","previous":0,"size":100,"diff":100},{"filename":"route-bylaws/index.tsx.chunk.*****.esm.js","previous":0,"size":8448,"diff":8448},{"filename":"route-contact/index.tsx.chunk.e324c.css","previous":0,"size":77,"diff":77},{"filename":"route-contact/index.tsx.chunk.*****.esm.js","previous":0,"size":534,"diff":534},{"filename":"route-home/index.tsx.chunk.e6c71.css","previous":0,"size":74,"diff":74},{"filename":"route-home/index.tsx.chunk.*****.esm.js","previous":0,"size":335,"diff":335},{"filename":"route-notfound/index.tsx.chunk.740b8.css","previous":0,"size":78,"diff":78},{"filename":"route-notfound/index.tsx.chunk.*****.esm.js","previous":0,"size":401,"diff":401},{"filename":"sw-esm.js","previous":0,"size":8457,"diff":8457},{"filename":"sw.js","previous":0,"size":8453,"diff":8453},{"filename":"bundle.f89f5.js","previous":0,"size":9554,"diff":9554},{"filename":"polyfills.2854d.js","previous":0,"size":2169,"diff":2169},{"filename":"route-about/index.tsx.chunk.b1496.js","previous":0,"size":731,"diff":731},{"filename":"route-art/index.tsx.chunk.2ae9c.js","previous":0,"size":341,"diff":341},{"filename":"route-bylaws/index.tsx.chunk.21202.js","previous":0,"size":8451,"diff":8451},{"filename":"route-contact/index.tsx.chunk.c46fb.js","previous":0,"size":535,"diff":535},{"filename":"route-home/index.tsx.chunk.a17d7.js","previous":0,"size":338,"diff":338},{"filename":"route-notfound/index.tsx.chunk.6e459.js","previous":0,"size":403,"diff":403}]},{"timestamp":1624340927308,"files":[{"filename":"bundle.66656.css","previous":645,"size":0,"diff":-645},{"filename":"bundle.*****.esm.js","previous":9582,"size":0,"diff":-9582},{"filename":"polyfills.*****.esm.js","previous":2173,"size":0,"diff":-2173},{"filename":"route-about/index.tsx.chunk.00f33.css","previous":75,"size":0,"diff":-75},{"filename":"route-about/index.tsx.chunk.*****.esm.js","previous":730,"size":0,"diff":-730},{"filename":"route-art/index.tsx.chunk.5684c.css","previous":73,"size":0,"diff":-73},{"filename":"route-art/index.tsx.chunk.*****.esm.js","previous":337,"size":0,"diff":-337},{"filename":"route-bylaws/index.tsx.chunk.d6322.css","previous":100,"size":0,"diff":-100},{"filename":"route-bylaws/index.tsx.chunk.*****.esm.js","previous":8448,"size":0,"diff":-8448},{"filename":"route-contact/index.tsx.chunk.e324c.css","previous":77,"size":0,"diff":-77},{"filename":"route-contact/index.tsx.chunk.*****.esm.js","previous":534,"size":0,"diff":-534},{"filename":"route-home/index.tsx.chunk.e6c71.css","previous":74,"size":0,"diff":-74},{"filename":"route-home/index.tsx.chunk.*****.esm.js","previous":335,"size":0,"diff":-335},{"filename":"route-notfound/index.tsx.chunk.740b8.css","previous":78,"size":0,"diff":-78},{"filename":"route-notfound/index.tsx.chunk.*****.esm.js","previous":401,"size":0,"diff":-401},{"filename":"sw-esm.js","previous":8457,"size":0,"diff":-8457},{"filename":"sw.js","previous":8453,"size":0,"diff":-8453},{"filename":"bundle.f89f5.js","previous":9554,"size":0,"diff":-9554},{"filename":"polyfills.2854d.js","previous":2169,"size":0,"diff":-2169},{"filename":"route-about/index.tsx.chunk.b1496.js","previous":731,"size":0,"diff":-731},{"filename":"route-art/index.tsx.chunk.2ae9c.js","previous":341,"size":0,"diff":-341},{"filename":"route-bylaws/index.tsx.chunk.21202.js","previous":8451,"size":0,"diff":-8451},{"filename":"route-contact/index.tsx.chunk.c46fb.js","previous":535,"size":0,"diff":-535},{"filename":"route-home/index.tsx.chunk.a17d7.js","previous":338,"size":0,"diff":-338},{"filename":"route-notfound/index.tsx.chunk.6e459.js","previous":403,"size":0,"diff":-403},{"filename":"ssr-bundle.db5e5.css","previous":0,"size":850,"diff":850},{"filename":"ssr-bundle.js","previous":0,"size":13496,"diff":13496}]},{"timestamp":1624340676280,"files":[{"filename":"ssr-bundle.db5e5.css","previous":850,"size":0,"diff":-850},{"filename":"ssr-bundle.js","previous":13496,"size":0,"diff":-13496},{"filename":"bundle.66656.css","previous":0,"size":645,"diff":645},{"filename":"bundle.*****.esm.js","previous":0,"size":9582,"diff":9582},{"filename":"polyfills.*****.esm.js","previous":0,"size":2173,"diff":2173},{"filename":"route-about/index.tsx.chunk.00f33.css","previous":0,"size":75,"diff":75},{"filename":"route-about/index.tsx.chunk.*****.esm.js","previous":0,"size":730,"diff":730},{"filename":"route-art/index.tsx.chunk.5684c.css","previous":0,"size":73,"diff":73},{"filename":"route-art/index.tsx.chunk.*****.esm.js","previous":0,"size":337,"diff":337},{"filename":"route-bylaws/index.tsx.chunk.d6322.css","previous":0,"size":100,"diff":100},{"filename":"route-bylaws/index.tsx.chunk.*****.esm.js","previous":0,"size":8448,"diff":8448},{"filename":"route-contact/index.tsx.chunk.e324c.css","previous":0,"size":77,"diff":77},{"filename":"route-contact/index.tsx.chunk.*****.esm.js","previous":0,"size":534,"diff":534},{"filename":"route-home/index.tsx.chunk.e6c71.css","previous":0,"size":74,"diff":74},{"filename":"route-home/index.tsx.chunk.*****.esm.js","previous":0,"size":335,"diff":335},{"filename":"route-notfound/index.tsx.chunk.740b8.css","previous":0,"size":78,"diff":78},{"filename":"route-notfound/index.tsx.chunk.*****.esm.js","previous":0,"size":401,"diff":401},{"filename":"sw-esm.js","previous":0,"size":8457,"diff":8457},{"filename":"sw.js","previous":0,"size":8453,"diff":8453},{"filename":"bundle.f89f5.js","previous":0,"size":9554,"diff":9554},{"filename":"polyfills.2854d.js","previous":0,"size":2169,"diff":2169},{"filename":"route-about/index.tsx.chunk.b1496.js","previous":0,"size":731,"diff":731},{"filename":"route-art/index.tsx.chunk.2ae9c.js","previous":0,"size":341,"diff":341},{"filename":"route-bylaws/index.tsx.chunk.21202.js","previous":0,"size":8451,"diff":8451},{"filename":"route-contact/index.tsx.chunk.c46fb.js","previous":0,"size":535,"diff":535},{"filename":"route-home/index.tsx.chunk.a17d7.js","previous":0,"size":338,"diff":338},{"filename":"route-notfound/index.tsx.chunk.6e459.js","previous":0,"size":403,"diff":403}]},{"timestamp":1624340662168,"files":[{"filename":"bundle.66656.css","previous":645,"size":0,"diff":-645},{"filename":"bundle.*****.esm.js","previous":9582,"size":0,"diff":-9582},{"filename":"polyfills.*****.esm.js","previous":2173,"size":0,"diff":-2173},{"filename":"route-about/index.tsx.chunk.00f33.css","previous":75,"size":0,"diff":-75},{"filename":"route-about/index.tsx.chunk.*****.esm.js","previous":730,"size":0,"diff":-730},{"filename":"route-art/index.tsx.chunk.5684c.css","previous":73,"size":0,"diff":-73},{"filename":"route-art/index.tsx.chunk.*****.esm.js","previous":337,"size":0,"diff":-337},{"filename":"route-bylaws/index.tsx.chunk.d6322.css","previous":100,"size":0,"diff":-100},{"filename":"route-bylaws/index.tsx.chunk.*****.esm.js","previous":8448,"size":0,"diff":-8448},{"filename":"route-contact/index.tsx.chunk.e324c.css","previous":77,"size":0,"diff":-77},{"filename":"route-contact/index.tsx.chunk.*****.esm.js","previous":534,"size":0,"diff":-534},{"filename":"route-home/index.tsx.chunk.e6c71.css","previous":74,"size":0,"diff":-74},{"filename":"route-home/index.tsx.chunk.*****.esm.js","previous":335,"size":0,"diff":-335},{"filename":"route-notfound/index.tsx.chunk.740b8.css","previous":78,"size":0,"diff":-78},{"filename":"route-notfound/index.tsx.chunk.*****.esm.js","previous":401,"size":0,"diff":-401},{"filename":"sw-esm.js","previous":8457,"size":0,"diff":-8457},{"filename":"sw.js","previous":8453,"size":0,"diff":-8453},{"filename":"bundle.f89f5.js","previous":9554,"size":0,"diff":-9554},{"filename":"polyfills.2854d.js","previous":2169,"size":0,"diff":-2169},{"filename":"route-about/index.tsx.chunk.b1496.js","previous":731,"size":0,"diff":-731},{"filename":"route-art/index.tsx.chunk.2ae9c.js","previous":341,"size":0,"diff":-341},{"filename":"route-bylaws/index.tsx.chunk.21202.js","previous":8451,"size":0,"diff":-8451},{"filename":"route-contact/index.tsx.chunk.c46fb.js","previous":535,"size":0,"diff":-535},{"filename":"route-home/index.tsx.chunk.a17d7.js","previous":338,"size":0,"diff":-338},{"filename":"route-notfound/index.tsx.chunk.6e459.js","previous":403,"size":0,"diff":-403},{"filename":"ssr-bundle.db5e5.css","previous":0,"size":850,"diff":850},{"filename":"ssr-bundle.js","previous":0,"size":13496,"diff":13496}]},{"timestamp":1624340497922,"files":[{"filename":"ssr-bundle.db5e5.css","previous":850,"size":0,"diff":-850},{"filename":"ssr-bundle.js","previous":13496,"size":0,"diff":-13496},{"filename":"bundle.66656.css","previous":0,"size":645,"diff":645},{"filename":"bundle.*****.esm.js","previous":0,"size":9582,"diff":9582},{"filename":"polyfills.*****.esm.js","previous":0,"size":2173,"diff":2173},{"filename":"route-about/index.tsx.chunk.00f33.css","previous":0,"size":75,"diff":75},{"filename":"route-about/index.tsx.chunk.*****.esm.js","previous":0,"size":730,"diff":730},{"filename":"route-art/index.tsx.chunk.5684c.css","previous":0,"size":73,"diff":73},{"filename":"route-art/index.tsx.chunk.*****.esm.js","previous":0,"size":337,"diff":337},{"filename":"route-bylaws/index.tsx.chunk.d6322.css","previous":0,"size":100,"diff":100},{"filename":"route-bylaws/index.tsx.chunk.*****.esm.js","previous":0,"size":8448,"diff":8448},{"filename":"route-contact/index.tsx.chunk.e324c.css","previous":0,"size":77,"diff":77},{"filename":"route-contact/index.tsx.chunk.*****.esm.js","previous":0,"size":534,"diff":534},{"filename":"route-home/index.tsx.chunk.e6c71.css","previous":0,"size":74,"diff":74},{"filename":"route-home/index.tsx.chunk.*****.esm.js","previous":0,"size":335,"diff":335},{"filename":"route-notfound/index.tsx.chunk.740b8.css","previous":0,"size":78,"diff":78},{"filename":"route-notfound/index.tsx.chunk.*****.esm.js","previous":0,"size":401,"diff":401},{"filename":"sw-esm.js","previous":0,"size":8457,"diff":8457},{"filename":"sw.js","previous":0,"size":8453,"diff":8453},{"filename":"bundle.f89f5.js","previous":0,"size":9554,"diff":9554},{"filename":"polyfills.2854d.js","previous":0,"size":2169,"diff":2169},{"filename":"route-about/index.tsx.chunk.b1496.js","previous":0,"size":731,"diff":731},{"filename":"route-art/index.tsx.chunk.2ae9c.js","previous":0,"size":341,"diff":341},{"filename":"route-bylaws/index.tsx.chunk.21202.js","previous":0,"size":8451,"diff":8451},{"filename":"route-contact/index.tsx.chunk.c46fb.js","previous":0,"size":535,"diff":535},{"filename":"route-home/index.tsx.chunk.a17d7.js","previous":0,"size":338,"diff":338},{"filename":"route-notfound/index.tsx.chunk.6e459.js","previous":0,"size":403,"diff":403}]},{"timestamp":1624340482762,"files":[{"filename":"bundle.66656.css","previous":645,"size":0,"diff":-645},{"filename":"bundle.*****.esm.js","previous":9582,"size":0,"diff":-9582},{"filename":"polyfills.*****.esm.js","previous":2173,"size":0,"diff":-2173},{"filename":"route-about/index.tsx.chunk.00f33.css","previous":75,"size":0,"diff":-75},{"filename":"route-about/index.tsx.chunk.*****.esm.js","previous":730,"size":0,"diff":-730},{"filename":"route-art/index.tsx.chunk.5684c.css","previous":73,"size":0,"diff":-73},{"filename":"route-art/index.tsx.chunk.*****.esm.js","previous":337,"size":0,"diff":-337},{"filename":"route-bylaws/index.tsx.chunk.d6322.css","previous":100,"size":0,"diff":-100},{"filename":"route-bylaws/index.tsx.chunk.*****.esm.js","previous":8448,"size":0,"diff":-8448},{"filename":"route-contact/index.tsx.chunk.e324c.css","previous":77,"size":0,"diff":-77},{"filename":"route-contact/index.tsx.chunk.*****.esm.js","previous":534,"size":0,"diff":-534},{"filename":"route-home/index.tsx.chunk.e6c71.css","previous":74,"size":0,"diff":-74},{"filename":"route-home/index.tsx.chunk.*****.esm.js","previous":335,"size":0,"diff":-335},{"filename":"route-notfound/index.tsx.chunk.740b8.css","previous":78,"size":0,"diff":-78},{"filename":"route-notfound/index.tsx.chunk.*****.esm.js","previous":401,"size":0,"diff":-401},{"filename":"sw-esm.js","previous":8457,"size":0,"diff":-8457},{"filename":"sw.js","previous":8453,"size":0,"diff":-8453},{"filename":"bundle.f89f5.js","previous":9554,"size":0,"diff":-9554},{"filename":"polyfills.2854d.js","previous":2169,"size":0,"diff":-2169},{"filename":"route-about/index.tsx.chunk.b1496.js","previous":731,"size":0,"diff":-731},{"filename":"route-art/index.tsx.chunk.2ae9c.js","previous":341,"size":0,"diff":-341},{"filename":"route-bylaws/index.tsx.chunk.21202.js","previous":8451,"size":0,"diff":-8451},{"filename":"route-contact/index.tsx.chunk.c46fb.js","previous":535,"size":0,"diff":-535},{"filename":"route-home/index.tsx.chunk.a17d7.js","previous":338,"size":0,"diff":-338},{"filename":"route-notfound/index.tsx.chunk.6e459.js","previous":403,"size":0,"diff":-403},{"filename":"ssr-bundle.db5e5.css","previous":0,"size":850,"diff":850},{"filename":"ssr-bundle.js","previous":0,"size":13496,"diff":13496}]},{"timestamp":1624340423427,"files":[{"filename":"ssr-bundle.db5e5.css","previous":850,"size":0,"diff":-850},{"filename":"ssr-bundle.js","previous":13496,"size":0,"diff":-13496},{"filename":"bundle.66656.css","previous":0,"size":645,"diff":645},{"filename":"bundle.*****.esm.js","previous":0,"size":9582,"diff":9582},{"filename":"polyfills.*****.esm.js","previous":0,"size":2173,"diff":2173},{"filename":"route-about/index.tsx.chunk.00f33.css","previous":0,"size":75,"diff":75},{"filename":"route-about/index.tsx.chunk.*****.esm.js","previous":0,"size":730,"diff":730},{"filename":"route-art/index.tsx.chunk.5684c.css","previous":0,"size":73,"diff":73},{"filename":"route-art/index.tsx.chunk.*****.esm.js","previous":0,"size":337,"diff":337},{"filename":"route-bylaws/index.tsx.chunk.d6322.css","previous":0,"size":100,"diff":100},{"filename":"route-bylaws/index.tsx.chunk.*****.esm.js","previous":0,"size":8448,"diff":8448},{"filename":"route-contact/index.tsx.chunk.e324c.css","previous":0,"size":77,"diff":77},{"filename":"route-contact/index.tsx.chunk.*****.esm.js","previous":0,"size":534,"diff":534},{"filename":"route-home/index.tsx.chunk.e6c71.css","previous":0,"size":74,"diff":74},{"filename":"route-home/index.tsx.chunk.*****.esm.js","previous":0,"size":335,"diff":335},{"filename":"route-notfound/index.tsx.chunk.740b8.css","previous":0,"size":78,"diff":78},{"filename":"route-notfound/index.tsx.chunk.*****.esm.js","previous":0,"size":401,"diff":401},{"filename":"sw-esm.js","previous":0,"size":8457,"diff":8457},{"filename":"sw.js","previous":0,"size":8453,"diff":8453},{"filename":"bundle.f89f5.js","previous":0,"size":9554,"diff":9554},{"filename":"polyfills.2854d.js","previous":0,"size":2169,"diff":2169},{"filename":"route-about/index.tsx.chunk.b1496.js","previous":0,"size":731,"diff":731},{"filename":"route-art/index.tsx.chunk.2ae9c.js","previous":0,"size":341,"diff":341},{"filename":"route-bylaws/index.tsx.chunk.21202.js","previous":0,"size":8451,"diff":8451},{"filename":"route-contact/index.tsx.chunk.c46fb.js","previous":0,"size":535,"diff":535},{"filename":"route-home/index.tsx.chunk.a17d7.js","previous":0,"size":338,"diff":338},{"filename":"route-notfound/index.tsx.chunk.6e459.js","previous":0,"size":403,"diff":403}]},{"timestamp":1624340409274,"files":[{"filename":"ssr-bundle.db5e5.css","previous":850,"size":850,"diff":0},{"filename":"ssr-bundle.js","previous":13504,"size":13496,"diff":-8}]},{"timestamp":1624340371025,"files":[{"filename":"bundle.f99f7.css","previous":521,"size":0,"diff":-521},{"filename":"bundle.*****.esm.js","previous":8486,"size":0,"diff":-8486},{"filename":"polyfills.*****.esm.js","previous":2173,"size":0,"diff":-2173},{"filename":"route-home/index.tsx.chunk.e6c71.css","previous":74,"size":0,"diff":-74},{"filename":"route-home/index.tsx.chunk.*****.esm.js","previous":288,"size":0,"diff":-288},{"filename":"route-notfound/index.tsx.chunk.c3378.css","previous":65,"size":0,"diff":-65},{"filename":"route-notfound/index.tsx.chunk.*****.esm.js","previous":331,"size":0,"diff":-331},{"filename":"route-profile/index.tsx.chunk.62c75.css","previous":77,"size":0,"diff":-77},{"filename":"route-profile/index.tsx.chunk.*****.esm.js","previous":1133,"size":0,"diff":-1133},{"filename":"sw-esm.js","previous":8457,"size":0,"diff":-8457},{"filename":"sw.js","previous":8453,"size":0,"diff":-8453},{"filename":"bundle.2efff.js","previous":8451,"size":0,"diff":-8451},{"filename":"polyfills.2854d.js","previous":2169,"size":0,"diff":-2169},{"filename":"route-home/index.tsx.chunk.67a4d.js","previous":291,"size":0,"diff":-291},{"filename":"route-notfound/index.tsx.chunk.e079d.js","previous":335,"size":0,"diff":-335},{"filename":"route-profile/index.tsx.chunk.a1bef.js","previous":1139,"size":0,"diff":-1139},{"filename":"ssr-bundle.db5e5.css","previous":0,"size":850,"diff":850},{"filename":"ssr-bundle.js","previous":0,"size":13504,"diff":13504}]},{"timestamp":1624330066035,"files":[{"filename":"ssr-bundle.43dcf.css","previous":682,"size":0,"diff":-682},{"filename":"ssr-bundle.js","previous":4253,"size":0,"diff":-4253},{"filename":"bundle.f99f7.css","previous":0,"size":521,"diff":521},{"filename":"bundle.*****.esm.js","previous":0,"size":8486,"diff":8486},{"filename":"polyfills.*****.esm.js","previous":0,"size":2173,"diff":2173},{"filename":"route-home/index.tsx.chunk.e6c71.css","previous":0,"size":74,"diff":74},{"filename":"route-home/index.tsx.chunk.*****.esm.js","previous":0,"size":288,"diff":288},{"filename":"route-notfound/index.tsx.chunk.c3378.css","previous":0,"size":65,"diff":65},{"filename":"route-notfound/index.tsx.chunk.*****.esm.js","previous":0,"size":331,"diff":331},{"filename":"route-profile/index.tsx.chunk.62c75.css","previous":0,"size":77,"diff":77},{"filename":"route-profile/index.tsx.chunk.*****.esm.js","previous":0,"size":1133,"diff":1133},{"filename":"sw-esm.js","previous":0,"size":8457,"diff":8457},{"filename":"sw.js","previous":0,"size":8453,"diff":8453},{"filename":"bundle.2efff.js","previous":0,"size":8451,"diff":8451},{"filename":"polyfills.2854d.js","previous":0,"size":2169,"diff":2169},{"filename":"route-home/index.tsx.chunk.67a4d.js","previous":0,"size":291,"diff":291},{"filename":"route-notfound/index.tsx.chunk.e079d.js","previous":0,"size":335,"diff":335},{"filename":"route-profile/index.tsx.chunk.a1bef.js","previous":0,"size":1139,"diff":1139}]},{"timestamp":1624330052810,"files":[{"filename":"bundle.f99f7.css","previous":521,"size":0,"diff":-521},{"filename":"bundle.*****.esm.js","previous":8486,"size":0,"diff":-8486},{"filename":"polyfills.*****.esm.js","previous":2173,"size":0,"diff":-2173},{"filename":"route-home/index.tsx.chunk.e6c71.css","previous":74,"size":0,"diff":-74},{"filename":"route-home/index.tsx.chunk.*****.esm.js","previous":288,"size":0,"diff":-288},{"filename":"route-notfound/index.tsx.chunk.c3378.css","previous":65,"size":0,"diff":-65},{"filename":"route-notfound/index.tsx.chunk.*****.esm.js","previous":331,"size":0,"diff":-331},{"filename":"route-profile/index.tsx.chunk.62c75.css","previous":77,"size":0,"diff":-77},{"filename":"route-profile/index.tsx.chunk.*****.esm.js","previous":1133,"size":0,"diff":-1133},{"filename":"sw-esm.js","previous":8457,"size":0,"diff":-8457},{"filename":"sw.js","previous":8453,"size":0,"diff":-8453},{"filename":"bundle.2efff.js","previous":8451,"size":0,"diff":-8451},{"filename":"polyfills.2854d.js","previous":2169,"size":0,"diff":-2169},{"filename":"route-home/index.tsx.chunk.67a4d.js","previous":291,"size":0,"diff":-291},{"filename":"route-notfound/index.tsx.chunk.e079d.js","previous":335,"size":0,"diff":-335},{"filename":"route-profile/index.tsx.chunk.a1bef.js","previous":1139,"size":0,"diff":-1139},{"filename":"ssr-bundle.43dcf.css","previous":0,"size":682,"diff":682},{"filename":"ssr-bundle.js","previous":0,"size":4253,"diff":4253}]},{"timestamp":1624330024814,"files":[{"filename":"ssr-bundle.43dcf.css","previous":682,"size":0,"diff":-682},{"filename":"ssr-bundle.js","previous":4253,"size":0,"diff":-4253},{"filename":"bundle.f99f7.css","previous":0,"size":521,"diff":521},{"filename":"bundle.*****.esm.js","previous":0,"size":8486,"diff":8486},{"filename":"polyfills.*****.esm.js","previous":0,"size":2173,"diff":2173},{"filename":"route-home/index.tsx.chunk.e6c71.css","previous":0,"size":74,"diff":74},{"filename":"route-home/index.tsx.chunk.*****.esm.js","previous":0,"size":288,"diff":288},{"filename":"route-notfound/index.tsx.chunk.c3378.css","previous":0,"size":65,"diff":65},{"filename":"route-notfound/index.tsx.chunk.*****.esm.js","previous":0,"size":331,"diff":331},{"filename":"route-profile/index.tsx.chunk.62c75.css","previous":0,"size":77,"diff":77},{"filename":"route-profile/index.tsx.chunk.*****.esm.js","previous":0,"size":1133,"diff":1133},{"filename":"sw-esm.js","previous":0,"size":8457,"diff":8457},{"filename":"sw.js","previous":0,"size":8453,"diff":8453},{"filename":"bundle.2efff.js","previous":0,"size":8451,"diff":8451},{"filename":"polyfills.2854d.js","previous":0,"size":2169,"diff":2169},{"filename":"route-home/index.tsx.chunk.67a4d.js","previous":0,"size":291,"diff":291},{"filename":"route-notfound/index.tsx.chunk.e079d.js","previous":0,"size":335,"diff":335},{"filename":"route-profile/index.tsx.chunk.a1bef.js","previous":0,"size":1139,"diff":1139}]},{"timestamp":1624330011899,"files":[{"filename":"bundle.f99f7.css","previous":521,"size":0,"diff":-521},{"filename":"bundle.*****.esm.js","previous":8486,"size":0,"diff":-8486},{"filename":"polyfills.*****.esm.js","previous":2173,"size":0,"diff":-2173},{"filename":"route-home/index.tsx.chunk.e6c71.css","previous":74,"size":0,"diff":-74},{"filename":"route-home/index.tsx.chunk.*****.esm.js","previous":288,"size":0,"diff":-288},{"filename":"route-notfound/index.tsx.chunk.c3378.css","previous":65,"size":0,"diff":-65},{"filename":"route-notfound/index.tsx.chunk.*****.esm.js","previous":331,"size":0,"diff":-331},{"filename":"route-profile/index.tsx.chunk.62c75.css","previous":77,"size":0,"diff":-77},{"filename":"route-profile/index.tsx.chunk.*****.esm.js","previous":1133,"size":0,"diff":-1133},{"filename":"sw.js","previous":8453,"size":0,"diff":-8453},{"filename":"sw-esm.js","previous":8457,"size":0,"diff":-8457},{"filename":"bundle.2efff.js","previous":8451,"size":0,"diff":-8451},{"filename":"polyfills.2854d.js","previous":2169,"size":0,"diff":-2169},{"filename":"route-home/index.tsx.chunk.67a4d.js","previous":291,"size":0,"diff":-291},{"filename":"route-notfound/index.tsx.chunk.e079d.js","previous":335,"size":0,"diff":-335},{"filename":"route-profile/index.tsx.chunk.a1bef.js","previous":1139,"size":0,"diff":-1139},{"filename":"ssr-bundle.43dcf.css","previous":0,"size":682,"diff":682},{"filename":"ssr-bundle.js","previous":0,"size":4253,"diff":4253}]},{"timestamp":1624329959154,"files":[{"filename":"ssr-bundle.43dcf.css","previous":682,"size":0,"diff":-682},{"filename":"ssr-bundle.js","previous":4253,"size":0,"diff":-4253},{"filename":"bundle.f99f7.css","previous":0,"size":521,"diff":521},{"filename":"bundle.*****.esm.js","previous":0,"size":8486,"diff":8486},{"filename":"polyfills.*****.esm.js","previous":0,"size":2173,"diff":2173},{"filename":"route-home/index.tsx.chunk.e6c71.css","previous":0,"size":74,"diff":74},{"filename":"route-home/index.tsx.chunk.*****.esm.js","previous":0,"size":288,"diff":288},{"filename":"route-notfound/index.tsx.chunk.c3378.css","previous":0,"size":65,"diff":65},{"filename":"route-notfound/index.tsx.chunk.*****.esm.js","previous":0,"size":331,"diff":331},{"filename":"route-profile/index.tsx.chunk.62c75.css","previous":0,"size":77,"diff":77},{"filename":"route-profile/index.tsx.chunk.*****.esm.js","previous":0,"size":1133,"diff":1133},{"filename":"sw.js","previous":0,"size":8453,"diff":8453},{"filename":"sw-esm.js","previous":0,"size":8457,"diff":8457},{"filename":"bundle.2efff.js","previous":0,"size":8451,"diff":8451},{"filename":"polyfills.2854d.js","previous":0,"size":2169,"diff":2169},{"filename":"route-home/index.tsx.chunk.67a4d.js","previous":0,"size":291,"diff":291},{"filename":"route-notfound/index.tsx.chunk.e079d.js","previous":0,"size":335,"diff":335},{"filename":"route-profile/index.tsx.chunk.a1bef.js","previous":0,"size":1139,"diff":1139}]},{"timestamp":1624329946916,"files":[{"filename":"bundle.f99f7.css","previous":521,"size":0,"diff":-521},{"filename":"bundle.*****.esm.js","previous":8486,"size":0,"diff":-8486},{"filename":"polyfills.*****.esm.js","previous":2173,"size":0,"diff":-2173},{"filename":"route-home/index.tsx.chunk.e6c71.css","previous":74,"size":0,"diff":-74},{"filename":"route-home/index.tsx.chunk.*****.esm.js","previous":288,"size":0,"diff":-288},{"filename":"route-notfound/index.tsx.chunk.c3378.css","previous":65,"size":0,"diff":-65},{"filename":"route-notfound/index.tsx.chunk.*****.esm.js","previous":331,"size":0,"diff":-331},{"filename":"route-profile/index.tsx.chunk.62c75.css","previous":77,"size":0,"diff":-77},{"filename":"route-profile/index.tsx.chunk.*****.esm.js","previous":1133,"size":0,"diff":-1133},{"filename":"sw.js","previous":8453,"size":0,"diff":-8453},{"filename":"sw-esm.js","previous":8457,"size":0,"diff":-8457},{"filename":"bundle.2efff.js","previous":8451,"size":0,"diff":-8451},{"filename":"polyfills.2854d.js","previous":2169,"size":0,"diff":-2169},{"filename":"route-home/index.tsx.chunk.67a4d.js","previous":291,"size":0,"diff":-291},{"filename":"route-notfound/index.tsx.chunk.e079d.js","previous":335,"size":0,"diff":-335},{"filename":"route-profile/index.tsx.chunk.a1bef.js","previous":1139,"size":0,"diff":-1139},{"filename":"ssr-bundle.43dcf.css","previous":0,"size":682,"diff":682},{"filename":"ssr-bundle.js","previous":0,"size":4253,"diff":4253}]},{"timestamp":1624328071423,"files":[{"filename":"ssr-bundle.43dcf.css","previous":682,"size":0,"diff":-682},{"filename":"ssr-bundle.js","previous":4253,"size":0,"diff":-4253},{"filename":"bundle.f99f7.css","previous":0,"size":521,"diff":521},{"filename":"bundle.*****.esm.js","previous":0,"size":8486,"diff":8486},{"filename":"polyfills.*****.esm.js","previous":0,"size":2173,"diff":2173},{"filename":"route-home/index.tsx.chunk.e6c71.css","previous":0,"size":74,"diff":74},{"filename":"route-home/index.tsx.chunk.*****.esm.js","previous":0,"size":288,"diff":288},{"filename":"route-notfound/index.tsx.chunk.c3378.css","previous":0,"size":65,"diff":65},{"filename":"route-notfound/index.tsx.chunk.*****.esm.js","previous":0,"size":331,"diff":331},{"filename":"route-profile/index.tsx.chunk.62c75.css","previous":0,"size":77,"diff":77},{"filename":"route-profile/index.tsx.chunk.*****.esm.js","previous":0,"size":1133,"diff":1133},{"filename":"sw.js","previous":0,"size":8453,"diff":8453},{"filename":"sw-esm.js","previous":0,"size":8457,"diff":8457},{"filename":"bundle.2efff.js","previous":0,"size":8451,"diff":8451},{"filename":"polyfills.2854d.js","previous":0,"size":2169,"diff":2169},{"filename":"route-home/index.tsx.chunk.67a4d.js","previous":0,"size":291,"diff":291},{"filename":"route-notfound/index.tsx.chunk.e079d.js","previous":0,"size":335,"diff":335},{"filename":"route-profile/index.tsx.chunk.a1bef.js","previous":0,"size":1139,"diff":1139}]},{"timestamp":1624328059068,"files":[{"filename":"bundle.f99f7.css","previous":521,"size":0,"diff":-521},{"filename":"bundle.*****.esm.js","previous":8486,"size":0,"diff":-8486},{"filename":"polyfills.*****.esm.js","previous":2173,"size":0,"diff":-2173},{"filename":"route-home/index.tsx.chunk.e6c71.css","previous":74,"size":0,"diff":-74},{"filename":"route-home/index.tsx.chunk.*****.esm.js","previous":288,"size":0,"diff":-288},{"filename":"route-notfound/index.tsx.chunk.c3378.css","previous":65,"size":0,"diff":-65},{"filename":"route-notfound/index.tsx.chunk.*****.esm.js","previous":331,"size":0,"diff":-331},{"filename":"route-profile/index.tsx.chunk.62c75.css","previous":77,"size":0,"diff":-77},{"filename":"route-profile/index.tsx.chunk.*****.esm.js","previous":1133,"size":0,"diff":-1133},{"filename":"sw.js","previous":8453,"size":0,"diff":-8453},{"filename":"sw-esm.js","previous":8457,"size":0,"diff":-8457},{"filename":"bundle.2efff.js","previous":8451,"size":0,"diff":-8451},{"filename":"polyfills.2854d.js","previous":2169,"size":0,"diff":-2169},{"filename":"route-home/index.tsx.chunk.67a4d.js","previous":291,"size":0,"diff":-291},{"filename":"route-notfound/index.tsx.chunk.e079d.js","previous":335,"size":0,"diff":-335},{"filename":"route-profile/index.tsx.chunk.a1bef.js","previous":1139,"size":0,"diff":-1139},{"filename":"ssr-bundle.43dcf.css","previous":0,"size":682,"diff":682},{"filename":"ssr-bundle.js","previous":0,"size":4253,"diff":4253}]},{"timestamp":1624328029874,"files":[{"filename":"ssr-bundle.43dcf.css","previous":682,"size":0,"diff":-682},{"filename":"ssr-bundle.js","previous":4253,"size":0,"diff":-4253},{"filename":"bundle.f99f7.css","previous":0,"size":521,"diff":521},{"filename":"bundle.*****.esm.js","previous":0,"size":8486,"diff":8486},{"filename":"polyfills.*****.esm.js","previous":0,"size":2173,"diff":2173},{"filename":"route-home/index.tsx.chunk.e6c71.css","previous":0,"size":74,"diff":74},{"filename":"route-home/index.tsx.chunk.*****.esm.js","previous":0,"size":288,"diff":288},{"filename":"route-notfound/index.tsx.chunk.c3378.css","previous":0,"size":65,"diff":65},{"filename":"route-notfound/index.tsx.chunk.*****.esm.js","previous":0,"size":331,"diff":331},{"filename":"route-profile/index.tsx.chunk.62c75.css","previous":0,"size":77,"diff":77},{"filename":"route-profile/index.tsx.chunk.*****.esm.js","previous":0,"size":1133,"diff":1133},{"filename":"sw.js","previous":0,"size":8453,"diff":8453},{"filename":"sw-esm.js","previous":0,"size":8457,"diff":8457},{"filename":"bundle.2efff.js","previous":0,"size":8451,"diff":8451},{"filename":"polyfills.2854d.js","previous":0,"size":2169,"diff":2169},{"filename":"route-home/index.tsx.chunk.67a4d.js","previous":0,"size":291,"diff":291},{"filename":"route-notfound/index.tsx.chunk.e079d.js","previous":0,"size":335,"diff":335},{"filename":"route-profile/index.tsx.chunk.a1bef.js","previous":0,"size":1139,"diff":1139}]},{"timestamp":1624328017359,"files":[{"filename":"bundle.f99f7.css","previous":521,"size":0,"diff":-521},{"filename":"bundle.*****.esm.js","previous":8486,"size":0,"diff":-8486},{"filename":"polyfills.*****.esm.js","previous":2173,"size":0,"diff":-2173},{"filename":"route-home/index.tsx.chunk.e6c71.css","previous":74,"size":0,"diff":-74},{"filename":"route-home/index.tsx.chunk.*****.esm.js","previous":288,"size":0,"diff":-288},{"filename":"route-notfound/index.tsx.chunk.c3378.css","previous":65,"size":0,"diff":-65},{"filename":"route-notfound/index.tsx.chunk.*****.esm.js","previous":331,"size":0,"diff":-331},{"filename":"route-profile/index.tsx.chunk.62c75.css","previous":77,"size":0,"diff":-77},{"filename":"route-profile/index.tsx.chunk.*****.esm.js","previous":1133,"size":0,"diff":-1133},{"filename":"sw.js","previous":8453,"size":0,"diff":-8453},{"filename":"sw-esm.js","previous":8457,"size":0,"diff":-8457},{"filename":"bundle.2efff.js","previous":8451,"size":0,"diff":-8451},{"filename":"polyfills.2854d.js","previous":2169,"size":0,"diff":-2169},{"filename":"route-home/index.tsx.chunk.67a4d.js","previous":291,"size":0,"diff":-291},{"filename":"route-notfound/index.tsx.chunk.e079d.js","previous":335,"size":0,"diff":-335},{"filename":"route-profile/index.tsx.chunk.a1bef.js","previous":1139,"size":0,"diff":-1139},{"filename":"ssr-bundle.43dcf.css","previous":0,"size":682,"diff":682},{"filename":"ssr-bundle.js","previous":0,"size":4253,"diff":4253}]},{"timestamp":1624327853085,"files":[{"filename":"ssr-bundle.43dcf.css","previous":682,"size":0,"diff":-682},{"filename":"ssr-bundle.js","previous":4253,"size":0,"diff":-4253},{"filename":"bundle.f99f7.css","previous":0,"size":521,"diff":521},{"filename":"bundle.*****.esm.js","previous":0,"size":8486,"diff":8486},{"filename":"polyfills.*****.esm.js","previous":0,"size":2173,"diff":2173},{"filename":"route-home/index.tsx.chunk.e6c71.css","previous":0,"size":74,"diff":74},{"filename":"route-home/index.tsx.chunk.*****.esm.js","previous":0,"size":288,"diff":288},{"filename":"route-notfound/index.tsx.chunk.c3378.css","previous":0,"size":65,"diff":65},{"filename":"route-notfound/index.tsx.chunk.*****.esm.js","previous":0,"size":331,"diff":331},{"filename":"route-profile/index.tsx.chunk.62c75.css","previous":0,"size":77,"diff":77},{"filename":"route-profile/index.tsx.chunk.*****.esm.js","previous":0,"size":1133,"diff":1133},{"filename":"sw.js","previous":0,"size":8453,"diff":8453},{"filename":"sw-esm.js","previous":0,"size":8457,"diff":8457},{"filename":"bundle.2efff.js","previous":0,"size":8451,"diff":8451},{"filename":"polyfills.2854d.js","previous":0,"size":2169,"diff":2169},{"filename":"route-home/index.tsx.chunk.67a4d.js","previous":0,"size":291,"diff":291},{"filename":"route-notfound/index.tsx.chunk.e079d.js","previous":0,"size":335,"diff":335},{"filename":"route-profile/index.tsx.chunk.a1bef.js","previous":0,"size":1139,"diff":1139}]},{"timestamp":1624327839441,"files":[{"filename":"bundle.f99f7.css","previous":521,"size":0,"diff":-521},{"filename":"bundle.*****.esm.js","previous":8486,"size":0,"diff":-8486},{"filename":"polyfills.*****.esm.js","previous":2173,"size":0,"diff":-2173},{"filename":"route-home/index.tsx.chunk.e6c71.css","previous":74,"size":0,"diff":-74},{"filename":"route-home/index.tsx.chunk.*****.esm.js","previous":288,"size":0,"diff":-288},{"filename":"route-notfound/index.tsx.chunk.c3378.css","previous":65,"size":0,"diff":-65},{"filename":"route-notfound/index.tsx.chunk.*****.esm.js","previous":331,"size":0,"diff":-331},{"filename":"route-profile/index.tsx.chunk.62c75.css","previous":77,"size":0,"diff":-77},{"filename":"route-profile/index.tsx.chunk.*****.esm.js","previous":1133,"size":0,"diff":-1133},{"filename":"sw.js","previous":8453,"size":0,"diff":-8453},{"filename":"sw-esm.js","previous":8457,"size":0,"diff":-8457},{"filename":"bundle.2efff.js","previous":8451,"size":0,"diff":-8451},{"filename":"polyfills.2854d.js","previous":2169,"size":0,"diff":-2169},{"filename":"route-home/index.tsx.chunk.67a4d.js","previous":291,"size":0,"diff":-291},{"filename":"route-notfound/index.tsx.chunk.e079d.js","previous":335,"size":0,"diff":-335},{"filename":"route-profile/index.tsx.chunk.a1bef.js","previous":1139,"size":0,"diff":-1139},{"filename":"ssr-bundle.43dcf.css","previous":0,"size":682,"diff":682},{"filename":"ssr-bundle.js","previous":0,"size":4253,"diff":4253}]},{"timestamp":1624327818187,"files":[{"filename":"ssr-bundle.43dcf.css","previous":682,"size":0,"diff":-682},{"filename":"ssr-bundle.js","previous":4253,"size":0,"diff":-4253},{"filename":"bundle.f99f7.css","previous":0,"size":521,"diff":521},{"filename":"bundle.*****.esm.js","previous":0,"size":8486,"diff":8486},{"filename":"polyfills.*****.esm.js","previous":0,"size":2173,"diff":2173},{"filename":"route-home/index.tsx.chunk.e6c71.css","previous":0,"size":74,"diff":74},{"filename":"route-home/index.tsx.chunk.*****.esm.js","previous":0,"size":288,"diff":288},{"filename":"route-notfound/index.tsx.chunk.c3378.css","previous":0,"size":65,"diff":65},{"filename":"route-notfound/index.tsx.chunk.*****.esm.js","previous":0,"size":331,"diff":331},{"filename":"route-profile/index.tsx.chunk.62c75.css","previous":0,"size":77,"diff":77},{"filename":"route-profile/index.tsx.chunk.*****.esm.js","previous":0,"size":1133,"diff":1133},{"filename":"sw.js","previous":0,"size":8453,"diff":8453},{"filename":"sw-esm.js","previous":0,"size":8457,"diff":8457},{"filename":"bundle.2efff.js","previous":0,"size":8451,"diff":8451},{"filename":"polyfills.2854d.js","previous":0,"size":2169,"diff":2169},{"filename":"route-home/index.tsx.chunk.67a4d.js","previous":0,"size":291,"diff":291},{"filename":"route-notfound/index.tsx.chunk.e079d.js","previous":0,"size":335,"diff":335},{"filename":"route-profile/index.tsx.chunk.a1bef.js","previous":0,"size":1139,"diff":1139}]},{"timestamp":1624327805457,"files":[{"filename":"bundle.f99f7.css","previous":521,"size":0,"diff":-521},{"filename":"bundle.*****.esm.js","previous":8486,"size":0,"diff":-8486},{"filename":"polyfills.*****.esm.js","previous":2173,"size":0,"diff":-2173},{"filename":"route-home/index.tsx.chunk.e6c71.css","previous":74,"size":0,"diff":-74},{"filename":"route-home/index.tsx.chunk.*****.esm.js","previous":288,"size":0,"diff":-288},{"filename":"route-notfound/index.tsx.chunk.c3378.css","previous":65,"size":0,"diff":-65},{"filename":"route-notfound/index.tsx.chunk.*****.esm.js","previous":331,"size":0,"diff":-331},{"filename":"route-profile/index.tsx.chunk.62c75.css","previous":77,"size":0,"diff":-77},{"filename":"route-profile/index.tsx.chunk.*****.esm.js","previous":1133,"size":0,"diff":-1133},{"filename":"sw-esm.js","previous":8457,"size":0,"diff":-8457},{"filename":"sw.js","previous":8453,"size":0,"diff":-8453},{"filename":"bundle.2efff.js","previous":8451,"size":0,"diff":-8451},{"filename":"polyfills.2854d.js","previous":2169,"size":0,"diff":-2169},{"filename":"route-home/index.tsx.chunk.67a4d.js","previous":291,"size":0,"diff":-291},{"filename":"route-notfound/index.tsx.chunk.e079d.js","previous":335,"size":0,"diff":-335},{"filename":"route-profile/index.tsx.chunk.a1bef.js","previous":1139,"size":0,"diff":-1139},{"filename":"ssr-bundle.43dcf.css","previous":0,"size":682,"diff":682},{"filename":"ssr-bundle.js","previous":0,"size":4253,"diff":4253}]},{"timestamp":1624327625812,"files":[{"filename":"ssr-bundle.43dcf.css","previous":682,"size":0,"diff":-682},{"filename":"ssr-bundle.js","previous":4253,"size":0,"diff":-4253},{"filename":"bundle.f99f7.css","previous":0,"size":521,"diff":521},{"filename":"bundle.*****.esm.js","previous":0,"size":8486,"diff":8486},{"filename":"polyfills.*****.esm.js","previous":0,"size":2173,"diff":2173},{"filename":"route-home/index.tsx.chunk.e6c71.css","previous":0,"size":74,"diff":74},{"filename":"route-home/index.tsx.chunk.*****.esm.js","previous":0,"size":288,"diff":288},{"filename":"route-notfound/index.tsx.chunk.c3378.css","previous":0,"size":65,"diff":65},{"filename":"route-notfound/index.tsx.chunk.*****.esm.js","previous":0,"size":331,"diff":331},{"filename":"route-profile/index.tsx.chunk.62c75.css","previous":0,"size":77,"diff":77},{"filename":"route-profile/index.tsx.chunk.*****.esm.js","previous":0,"size":1133,"diff":1133},{"filename":"sw-esm.js","previous":0,"size":8457,"diff":8457},{"filename":"sw.js","previous":0,"size":8453,"diff":8453},{"filename":"bundle.2efff.js","previous":0,"size":8451,"diff":8451},{"filename":"polyfills.2854d.js","previous":0,"size":2169,"diff":2169},{"filename":"route-home/index.tsx.chunk.67a4d.js","previous":0,"size":291,"diff":291},{"filename":"route-notfound/index.tsx.chunk.e079d.js","previous":0,"size":335,"diff":335},{"filename":"route-profile/index.tsx.chunk.a1bef.js","previous":0,"size":1139,"diff":1139}]},{"timestamp":1624327611203,"files":[{"filename":"bundle.7e56a.css","previous":445,"size":0,"diff":-445},{"filename":"bundle.*****.esm.js","previous":8486,"size":0,"diff":-8486},{"filename":"polyfills.*****.esm.js","previous":2173,"size":0,"diff":-2173},{"filename":"route-home/index.tsx.chunk.e6c71.css","previous":74,"size":0,"diff":-74},{"filename":"route-home/index.tsx.chunk.*****.esm.js","previous":288,"size":0,"diff":-288},{"filename":"route-notfound/index.tsx.chunk.c3378.css","previous":65,"size":0,"diff":-65},{"filename":"route-notfound/index.tsx.chunk.*****.esm.js","previous":331,"size":0,"diff":-331},{"filename":"route-profile/index.tsx.chunk.62c75.css","previous":77,"size":0,"diff":-77},{"filename":"route-profile/index.tsx.chunk.*****.esm.js","previous":1133,"size":0,"diff":-1133},{"filename":"sw-esm.js","previous":8457,"size":0,"diff":-8457},{"filename":"sw.js","previous":8453,"size":0,"diff":-8453},{"filename":"bundle.47b92.js","previous":8455,"size":0,"diff":-8455},{"filename":"polyfills.2854d.js","previous":2169,"size":0,"diff":-2169},{"filename":"route-home/index.tsx.chunk.67a4d.js","previous":291,"size":0,"diff":-291},{"filename":"route-notfound/index.tsx.chunk.e079d.js","previous":335,"size":0,"diff":-335},{"filename":"route-profile/index.tsx.chunk.a1bef.js","previous":1139,"size":0,"diff":-1139},{"filename":"ssr-bundle.43dcf.css","previous":0,"size":682,"diff":682},{"filename":"ssr-bundle.js","previous":0,"size":4253,"diff":4253}]},{"timestamp":1624304273238,"files":[{"filename":"ssr-bundle.ac348.css","previous":602,"size":0,"diff":-602},{"filename":"ssr-bundle.js","previous":4253,"size":0,"diff":-4253},{"filename":"bundle.7e56a.css","previous":0,"size":445,"diff":445},{"filename":"bundle.*****.esm.js","previous":0,"size":8486,"diff":8486},{"filename":"polyfills.*****.esm.js","previous":0,"size":2173,"diff":2173},{"filename":"route-home/index.tsx.chunk.e6c71.css","previous":0,"size":74,"diff":74},{"filename":"route-home/index.tsx.chunk.*****.esm.js","previous":0,"size":288,"diff":288},{"filename":"route-notfound/index.tsx.chunk.c3378.css","previous":0,"size":65,"diff":65},{"filename":"route-notfound/index.tsx.chunk.*****.esm.js","previous":0,"size":331,"diff":331},{"filename":"route-profile/index.tsx.chunk.62c75.css","previous":0,"size":77,"diff":77},{"filename":"route-profile/index.tsx.chunk.*****.esm.js","previous":0,"size":1133,"diff":1133},{"filename":"sw-esm.js","previous":0,"size":8457,"diff":8457},{"filename":"sw.js","previous":0,"size":8453,"diff":8453},{"filename":"bundle.47b92.js","previous":0,"size":8455,"diff":8455},{"filename":"polyfills.2854d.js","previous":0,"size":2169,"diff":2169},{"filename":"route-home/index.tsx.chunk.67a4d.js","previous":0,"size":291,"diff":291},{"filename":"route-notfound/index.tsx.chunk.e079d.js","previous":0,"size":335,"diff":335},{"filename":"route-profile/index.tsx.chunk.a1bef.js","previous":0,"size":1139,"diff":1139}]},{"timestamp":1624304258616,"files":[{"filename":"ssr-bundle.ac348.css","previous":0,"size":602,"diff":602},{"filename":"ssr-bundle.js","previous":0,"size":4253,"diff":4253}]}]
